pycounts_yz110/__init__.py
pycounts_yz110/plotting.py
pycounts_yz110/pycounts.py
pycounts_yz110-0.1.0.dist-info/LICENSE
pycounts_yz110-0.1.0.dist-info/METADATA
pycounts_yz110-0.1.0.dist-info/WHEEL
pycounts_yz110-0.1.0.dist-info/RECORD
